bruteforceDict/__init__.py
bruteforceDict/bruteforceDict.py
bruteforceDict-0.0.dist-info/METADATA
bruteforceDict-0.0.dist-info/WHEEL
bruteforceDict-0.0.dist-info/top_level.txt
bruteforceDict-0.0.dist-info/RECORD
