Metadata-Version: 2.1
Name: bruteforceDict
Version: 0.0
Summary: Bruteforce to file, to array
Home-page: UNKNOWN
Author: UNKNOWN
Author-email: yura@anisimoff.tel
License: UNKNOWN
Platform: UNKNOWN
